{
    "AlternateBaseBackground": "#d9d9d9",
    "AlternateWindowBackground": "#e3e3e3",
    "Base": "#ffffff",
    "BrightText": "#FF0000",
    "ButtonBackground": "#eeeef6",
    "ButtonText": "#3c3c77",
    "DisabledAlternateBase": "#eeeef6",
    "DisabledBase": "#d9d9d9",
    "DisabledBrightText": "#FF0000",
    "DisabledButton": "#eeeef6",
    "DisabledButtonText": "#eeeef6",
    "DisabledHighlight": "#2A82DA",
    "DisabledHighlightText": "#3c3c77",
    "DisabledLink": "#2A82DA",
    "DisabledText": "#3c3c77",
    "DisabledTooltip": "#3c3c77",
    "DisabledTooltipText": "#3c3c77",
    "DisabledWindow": "#eeeef6",
    "DisabledWindowText": "#3c3c77",
    "Highlight": "#D9B36D",
    "HighlightDark": "#B2842E",
    "HighlightedText": "#3c3c77",
    "Link": "#2A82DA",
    "Text": "#3c3c77",
    "TooltipBase": "#ffffdc",
    "TooltipText": "#3c3c77",
    "WindowBackground": "#efefef",
    "WindowText": "#3c3c77",
    "plotBg": "#d9d9d9",
    "plot_a": "#BB3E03",
    "plot_b": "#0066cc",
    "plot_bgr": "#7d8ea0",
    "plot_c": "#822433",
    "plot_db": "#003359",
    "plot_g": "#AE2012",
    "plot_gr": "#999999",
    "plot_la": "#94D2BD",
    "plot_lb": "#001219",
    "plot_mb": "#0076a9",
    "plot_o": "#CA6702",
    "plot_p": "#0A9396",
    "plot_r": "#EE9B00",
    "plot_ro": "#f23f00",
    "plot_t": "#005F73",
    "plot_wgr": "#82786f",
    "plot_y": "#AE2012"
}